README.rst
setup.py
papi/__init__.py
papi/exceptions.py
papi/fp.py
papi/hateoas.py
papi/method_override_middleware.py
papi/mime.py
papi/paths.py
papi/request.py
papi/resource.py
papi/serve.py
papi.egg-info/PKG-INFO
papi.egg-info/SOURCES.txt
papi.egg-info/dependency_links.txt
papi.egg-info/requires.txt
papi.egg-info/top_level.txt