Metadata-Version: 1.1
Name: papi
Version: 0.1.7
Summary: Build RESTful APIs with minimal boilerplate
Home-page: https://github.com/tracksinspector/papi
Author: Tobias Dammers
Author-email: dammers@tracksinspector.com
License: MIT
Keywords: restful rest webservice json http hateoas
Platform: UNKNOWN
Classifier: Development Status :: 4 - Beta
Classifier: Intended Audience :: Developers
Classifier: Topic :: Internet :: WWW/HTTP :: Dynamic Content
Classifier: License :: OSI Approved :: MIT License
Classifier: Programming Language :: Python :: 3
Classifier: Programming Language :: Python :: 3.3
Classifier: Programming Language :: Python :: 3.4
Classifier: Programming Language :: Python :: 3.5
